LICENSE
MANIFEST.in
README.md
pyproject.toml
setup.cfg
setup.py
versioneer.py
merlin/dataloader/__init__.py
merlin/dataloader/_version.py
merlin/dataloader/jax.py
merlin/dataloader/loader_base.py
merlin/dataloader/tensorflow.py
merlin/dataloader/tf_utils.py
merlin/dataloader/torch.py
merlin/dataloader/ops/__init__.py
merlin/dataloader/ops/embeddings.py
merlin/dataloader/ops/padding.py
merlin/dataloader/utils/tf/tf_trainer.py
merlin/dataloader/utils/torch/torch_trainer_dist.py
merlin/loader/__init__.py
merlin/loader/jax.py
merlin/loader/tensorflow.py
merlin/loader/torch.py
merlin_dataloader.egg-info/PKG-INFO
merlin_dataloader.egg-info/SOURCES.txt
merlin_dataloader.egg-info/dependency_links.txt
merlin_dataloader.egg-info/requires.txt
merlin_dataloader.egg-info/top_level.txt
requirements/base.txt
requirements/dev.txt
requirements/docs.txt
requirements/jax.txt
requirements/tensorflow.txt
requirements/torch.txt