Metadata-Version: 2.1
Name: merlin-dataloader
Version: 23.5.0
Summary: Merlin Dataloader
Home-page: https://github.com/NVIDIA-Merlin/dataloader
Author: NVIDIA Corporation
License: Apache 2.0
Platform: UNKNOWN
Classifier: Development Status :: 4 - Beta
Classifier: Programming Language :: Python :: 3
Classifier: Programming Language :: Python :: 3.8
Classifier: Programming Language :: Python :: 3.9
Classifier: Programming Language :: Python :: 3.10
Classifier: Programming Language :: Python :: 3 :: Only
Classifier: Intended Audience :: Developers
Classifier: License :: OSI Approved :: Apache Software License
Classifier: Topic :: Software Development :: Libraries
Classifier: Topic :: Scientific/Engineering
Requires-Python: >=3.8
Provides-Extra: base
Provides-Extra: tensorflow
Provides-Extra: pytorch
Provides-Extra: torch
Provides-Extra: jax
Provides-Extra: dev
Provides-Extra: all
License-File: LICENSE
